kavanoz/__init__.py
kavanoz/core.py
kavanoz/debug_utils.py
kavanoz/plugin_loader.py
kavanoz/smali_regexes.py
kavanoz/unpack_plugin.py
kavanoz/utils.py
kavanoz/loader/__init__.py
kavanoz/loader/appsealing.py
kavanoz/loader/coper.py
kavanoz/loader/crocodile.py
kavanoz/loader/kangapack.py
kavanoz/loader/moqhao.py
kavanoz/loader/multidex.py
kavanoz/loader/multidex_header.py
kavanoz/loader/old_rc4.py
kavanoz/loader/pronlocker.py
kavanoz/loader/rc4.py
kavanoz/loader/sesdex.py
kavanoz/loader/simple.py
kavanoz/loader/simple_aes.py
kavanoz/loader/simple_xor.py
kavanoz/loader/simple_xor_zlib.py
kavanoz/loader/simply_xor2.py
kavanoz/loader/subapp.py
kavanoz/loader/androidnativeemu/libc.so
kavanoz-0.0.6.dist-info/licenses/LICENSE
kavanoz-0.0.6.dist-info/METADATA
kavanoz-0.0.6.dist-info/WHEEL
kavanoz-0.0.6.dist-info/entry_points.txt
kavanoz-0.0.6.dist-info/top_level.txt
kavanoz-0.0.6.dist-info/RECORD
