Metadata-Version: 2.4
Name: kavanoz
Version: 0.0.6
Summary: Unpacking framework for common android malware
Author: Ahmet Bilal Can
Author-email: eybisii@gmail.com
Maintainer-email: Ahmet Bilal Can <eybisii@gmail.com>
License: MIT License
Keywords: android,malware,unpacking,packer
License-File: LICENSE
Requires-Dist: androguard>=4.0.1
Requires-Dist: apkInspector>=1.2.1
Requires-Dist: androidemu>=0.0.4
Requires-Dist: arc4>=0.3.0
Requires-Dist: halo>=0.0.31
Requires-Dist: lief>=0.16.3
Requires-Dist: loguru>=0.7.2
Requires-Dist: pycryptodome>=3.19.1
Dynamic: license-file
